libnncase.simulator.k230.so
libnncase.simulator.xpu.so
nncase.simulator.k230.sc
nncase/modules/kpu/Nncase.Modules.K230.dll
nncase_kpu-2.10.0.data/purelib/nncase_kpu/__init__.py
nncase_kpu.libs/libuuid-f64cda11.so.1.3.0
nncase_kpu-2.10.0.dist-info/LICENSE
nncase_kpu-2.10.0.dist-info/METADATA
nncase_kpu-2.10.0.dist-info/WHEEL
nncase_kpu-2.10.0.dist-info/top_level.txt
nncase_kpu-2.10.0.dist-info/RECORD
