Metadata-Version: 2.1
Name: nncase-kpu
Version: 2.10.0
Summary: kpu plug-in for nncase
Author: sunnycase
Author-email: guohui@canaan-creative.com
Maintainer: sunnycase
Maintainer-email: guohui@canaan-creative.com
License: 
Project-URL: Homepage, https://g.a-bug.org/software/k80/nncase/nncase-k80
Project-URL: documentation, https://g.a-bug.org/software/k80/nncase/nncase-k80
Project-URL: repository, https://g.a-bug.org/software/k80/nncase/nncase-k80
Keywords: kendryte,nn,compiler,k510,k230
Classifier: Programming Language :: C++
Classifier: Programming Language :: Python :: 3
Classifier: Programming Language :: Python :: 3.9
Classifier: Programming Language :: Python :: 3.10
Classifier: Programming Language :: Python :: 3.11
Classifier: Programming Language :: Python :: 3.12
Classifier: Programming Language :: Python :: 3.13
Classifier: License :: OSI Approved :: Apache Software License
Classifier: Operating System :: OS Independent
Requires-Python: >=3.9
License-File: LICENSE
Dynamic: license-file
Requires-Dist: nncase (>=2.10.0)
